hydrafloods/MODIS_DNNS.py
hydrafloods/VIIRS_DNNS.py
hydrafloods/__init__.py
hydrafloods/corrections.py
hydrafloods/datasets.py
hydrafloods/decorators.py
hydrafloods/defaults.py
hydrafloods/depths.py
hydrafloods/fetch.py
hydrafloods/filtering.py
hydrafloods/floods.py
hydrafloods/fusion.py
hydrafloods/fuzzy.py
hydrafloods/geeutils.py
hydrafloods/indices.py
hydrafloods/ml.py
hydrafloods/thresholding.py
hydrafloods/timeseries.py
hydrafloods/utils.py
hydrafloods/workflows/__init__.py
hydrafloods/workflows/dswfp.py
hydrafloods/workflows/hydrosar.py
hydrafloods-2023.10.14.dist-info/LICENSE
hydrafloods-2023.10.14.dist-info/METADATA
hydrafloods-2023.10.14.dist-info/WHEEL
hydrafloods-2023.10.14.dist-info/entry_points.txt
hydrafloods-2023.10.14.dist-info/top_level.txt
hydrafloods-2023.10.14.dist-info/RECORD
