Metadata-Version: 2.1
Name: hydrafloods
Version: 2023.10.14
Summary: HYDrologic Remote sensing Analysis for Floods
Home-page: http://github.com/servir-mekong/hydra-floods
Author: Kel Markert
Author-email: kel.markert@gmail.com
License: GNU GPL v3.0
License-File: LICENSE
Requires-Dist: simplecmr
Requires-Dist: earthengine-api
Requires-Dist: gcsfs
Requires-Dist: fire
Requires-Dist: pipetools
